gimmik/__init__.py
gimmik/_version.py
gimmik/base.py
gimmik/c.py
gimmik/copenmp.py
gimmik/cuda.py
gimmik/hip.py
gimmik/ispc.py
gimmik/metal.py
gimmik/opencl.py
gimmik/kernels/c/cstream.mako
gimmik/kernels/c-openmp/cstream.mako
gimmik/kernels/cuda/base.mako
gimmik/kernels/cuda/bstream-msplit.mako
gimmik/kernels/cuda/bstream.mako
gimmik/kernels/cuda/cstream-ksplit.mako
gimmik/kernels/cuda/cstream.mako
gimmik/kernels/hip/base.mako
gimmik/kernels/hip/bstream-msplit.mako
gimmik/kernels/hip/bstream.mako
gimmik/kernels/hip/cstream-ksplit.mako
gimmik/kernels/hip/cstream.mako
gimmik/kernels/ispc/cstream.mako
gimmik/kernels/metal/base.mako
gimmik/kernels/metal/bstream-msplit.mako
gimmik/kernels/metal/bstream.mako
gimmik/kernels/metal/cstream-ksplit.mako
gimmik/kernels/metal/cstream.mako
gimmik/kernels/opencl/bstream-msplit.mako
gimmik/kernels/opencl/bstream.mako
gimmik/kernels/opencl/cstream-ksplit.mako
gimmik/kernels/opencl/cstream.mako
gimmik-3.2.1.dist-info/AUTHORS
gimmik-3.2.1.dist-info/LICENSE
gimmik-3.2.1.dist-info/METADATA
gimmik-3.2.1.dist-info/WHEEL
gimmik-3.2.1.dist-info/top_level.txt
gimmik-3.2.1.dist-info/RECORD
