Metadata-Version: 2.1
Name: gimmik
Version: 3.2.1
Summary: Generator of Matrix Multiplication Kernels
Home-page: https://github.com/vincentlab/GiMMiK
Maintainer: Freddie Witherden
Maintainer-email: freddie@witherden.org
License: BSD
Keywords: Matrix Multiplication,ISPC,GPU,CUDA,HIP,Metal,OpenCL
Classifier: License :: OSI Approved :: BSD License
Classifier: Programming Language :: Python :: 3.9
Classifier: Programming Language :: Python :: 3.10
Classifier: Programming Language :: Python :: 3.11
Classifier: Topic :: Scientific/Engineering
License-File: LICENSE
License-File: AUTHORS
Requires-Dist: mako
Requires-Dist: numpy >=1.7
